[
  {
    "Course ID": "ASU 101",
    "Course Name": "The ASU Experience",
    "Course Number": "26347",
    "Teacher": "Dunn",
    "Course Days": "T",
    "Course Start Time": "10:30 AM",
    "Course End Time": "11:20 AM",
    "Course Location": "Tempe - BYENG361",
    "Start/End dates": "01/11 - 04/30(C)",
    "Course Hours": "1",
    "Occupado": "10 of 19",
    "IDC1": "",
    "IDC2": ""
  },
  {
    "Course ID": "ASU 101",
    "Course Name": "The ASU Experience",
    "Course Number": "27028",
    "Teacher": "Dunn",
    "Course Days": "Th",
    "Course Start Time": "3:00 PM",
    "Course End Time": "3:50 PM",
    "Course Location": "Tempe - BYENG361",
    "Start/End dates": "01/11 - 04/30(C)",
    "Course Hours": "1",
    "Occupado": "8 of 19",
    "IDC1": "",
    "IDC2": ""
  },
  {
    "Course ID": "ASU 101",
    "Course Name": "The ASU Experience",
    "Course Number": "27029",
    "Teacher": "Dunn",
    "Course Days": "Th",
    "Course Start Time": "10:30 AM",
    "Course End Time": "11:20 AM",
    "Course Location": "Tempe - BYENG361",
    "Start/End dates": "01/11 - 04/30(C)",
    "Course Hours": "1",
    "Occupado": "15 of 19",
    "IDC1": "",
    "IDC2": ""
  },
  {
    "Course ID": "ASU 101",
    "Course Name": "The ASU Experience",
    "Course Number": "29945",
    "Teacher": "Kobayashi",
    "Course Days": "Th",
    "Course Start Time": "1:30 PM",
    "Course End Time": "2:20 PM",
    "Course Location": "Tempe - BYENG361",
    "Start/End dates": "01/11 - 04/30(C)",
    "Course Hours": "1",
    "Occupado": "19 of 19",
    "IDC1": "",
    "IDC2": ""
  },
  {
    "Course ID": "ASU 101",
    "Course Name": "The ASU Experience",
    "Course Number": "30825",
    "Teacher": "Hsiao",
    "Course Days": "W",
    "Course Start Time": "10:10 AM",
    "Course End Time": "11:00 AM",
    "Course Location": "Tempe - BYENG361",
    "Start/End dates": "01/11 - 04/30(C)",
    "Course Hours": "1",
    "Occupado": "9 of 19",
    "IDC1": "",
    "IDC2": ""
  },
  {
    "Course ID": "ASU 101",
    "Course Name": "The ASU Experience",
    "Course Number": "30826",
    "Teacher": "Kobayashi",
    "Course Days": "M",
    "Course Start Time": "3:35 PM",
    "Course End Time": "4:25 PM",
    "Course Location": "Tempe - BYENG361",
    "Start/End dates": "01/11 - 04/30(C)",
    "Course Hours": "1",
    "Occupado": "15 of 19",
    "IDC1": "",
    "IDC2": ""
  },
  {
    "Course ID": "ASU 101",
    "Course Name": "The ASU Experience",
    "Course Number": "30827",
    "Teacher": "Kobayashi",
    "Course Days": "W",
    "Course Start Time": "3:35 PM",
    "Course End Time": "4:25 PM",
    "Course Location": "Tempe - BYENG361",
    "Start/End dates": "01/11 - 04/30(C)",
    "Course Hours": "1",
    "Occupado": "18 of 19",
    "IDC1": "",
    "IDC2": ""
  }
]
